datasette_proxy_image_tags/__init__.py
datasette_proxy_image_tags-0.4.dist-info/LICENSE
datasette_proxy_image_tags-0.4.dist-info/METADATA
datasette_proxy_image_tags-0.4.dist-info/WHEEL
datasette_proxy_image_tags-0.4.dist-info/entry_points.txt
datasette_proxy_image_tags-0.4.dist-info/top_level.txt
datasette_proxy_image_tags-0.4.dist-info/RECORD
