Metadata-Version: 2.1
Name: datasette-proxy-image-tags
Version: 0.4
Summary: Proxy and render blocked cross-origin images in datasette cells
Home-page: https://github.com/redraw/datasette-proxy-image-tags
Author: redraw
License: Apache License, Version 2.0
Project-URL: Issues, https://github.com/redraw/datasette-proxy-image-tags/issues
Project-URL: CI, https://github.com/redraw/datasette-proxy-image-tags/actions
Project-URL: Changelog, https://github.com/redraw/datasette-proxy-image-tags/releases
Classifier: Framework :: Datasette
Classifier: License :: OSI Approved :: Apache Software License
Requires-Python: >=3.7
License-File: LICENSE
Requires-Dist: datasette
Provides-Extra: test
Requires-Dist: pytest ; extra == 'test'
Requires-Dist: pytest-asyncio ; extra == 'test'
